serialix/__init__.py
serialix/cli.py
serialix/core.py
serialix/langs.py
serialix/meta.py
serialix/serialix.py
serialix/formats/__init__.py
serialix/formats/json.py
serialix/formats/toml.py
serialix/formats/yaml.py
serialix/tests/__init__.py
serialix/tests/conftest.py
serialix/tests/core.py
serialix/tests/test_json.py
serialix/tests/test_toml.py
serialix/tests/test_ujson.py
serialix/tests/test_yaml.py
serialix-2.4.1.dist-info/LICENSE
serialix-2.4.1.dist-info/METADATA
serialix-2.4.1.dist-info/WHEEL
serialix-2.4.1.dist-info/entry_points.txt
serialix-2.4.1.dist-info/top_level.txt
serialix-2.4.1.dist-info/RECORD
