Metadata-Version: 2.1
Name: serialix
Version: 2.4.1
Summary: Powerful and easy to use api for working with various human-readable data serialization formats
Home-page: https://github.com/maximilionus/serialix
Author: maximilionus
Author-email: maximilionuss@gmail.com
License: MIT
Project-URL: Documentation, https://maximilionus.github.io/serialix
Project-URL: Tracker, https://github.com/maximilionus/serialix/issues
Keywords: serialization format files parse json yaml toml
Platform: UNKNOWN
Classifier: License :: OSI Approved :: MIT License
Classifier: Operating System :: OS Independent
Classifier: Development Status :: 5 - Production/Stable
Classifier: Programming Language :: Python :: 3 :: Only
Classifier: Programming Language :: Python :: 3
Classifier: Programming Language :: Python :: 3.5
Classifier: Programming Language :: Python :: 3.6
Classifier: Programming Language :: Python :: 3.7
Classifier: Programming Language :: Python :: 3.8
Classifier: Programming Language :: Python :: 3.9
Classifier: Programming Language :: Python :: 3.10
Classifier: Intended Audience :: Developers
Classifier: Intended Audience :: Information Technology
Classifier: Topic :: Software Development :: Libraries
Classifier: Topic :: Text Processing
Requires-Python: ~=3.5
License-File: LICENSE
Provides-Extra: full
Requires-Dist: ujson (<=6.0.0) ; extra == 'full'
Requires-Dist: ruamel.yaml (<=1.0.0) ; extra == 'full'
Requires-Dist: toml (<=1.0.0) ; extra == 'full'
Provides-Extra: test
Requires-Dist: ujson (<=6.0.0) ; extra == 'test'
Requires-Dist: ruamel.yaml (<=1.0.0) ; extra == 'test'
Requires-Dist: toml (<=1.0.0) ; extra == 'test'
Requires-Dist: pytest (<7) ; extra == 'test'
Provides-Extra: toml
Requires-Dist: toml (<=1.0.0) ; extra == 'toml'
Provides-Extra: ujson
Requires-Dist: ujson (<=6.0.0) ; extra == 'ujson'
Provides-Extra: yaml
Requires-Dist: ruamel.yaml (<=1.0.0) ; extra == 'yaml'
